[
  {
    "state": "Andhra Pradesh",
    "petrol": "109.83",
    "diesel": "97.66",
    "updated": "2026-03-01"
  },
  {
    "state": "Arunachal Pradesh",
    "petrol": "90.67",
    "diesel": "80.21",
    "updated": "2026-03-01"
  },
  {
    "state": "Assam",
    "petrol": "98.28",
    "diesel": "89.50",
    "updated": "2026-03-01"
  },
  {
    "state": "Bihar",
    "petrol": "105.59",
    "diesel": "91.82",
    "updated": "2026-03-01"
  },
  {
    "state": "Chhattisgarh",
    "petrol": "105.00",
    "diesel": "96.20",
    "updated": "2026-03-01"
  },
  {
    "state": "Delhi",
    "petrol": "94.77",
    "diesel": "87.67",
    "updated": "2026-03-01"
  },
  {
    "state": "Goa",
    "petrol": "96.61",
    "diesel": "88.37",
    "updated": "2026-03-01"
  },
  {
    "state": "Gujarat",
    "petrol": "94.97",
    "diesel": "90.65",
    "updated": "2026-03-01"
  },
  {
    "state": "Haryana",
    "petrol": "95.95",
    "diesel": "88.40",
    "updated": "2026-03-01"
  },
  {
    "state": "Himachal Pradesh",
    "petrol": "94.98",
    "diesel": "86.95",
    "updated": "2026-03-01"
  },
  {
    "state": "Jharkhand",
    "petrol": "97.86",
    "diesel": "92.62",
    "updated": "2026-03-01"
  },
  {
    "state": "Karnataka",
    "petrol": "102.96",
    "diesel": "90.99",
    "updated": "2026-03-01"
  },
  {
    "state": "Kerala",
    "petrol": "107.48",
    "diesel": "96.48",
    "updated": "2026-03-01"
  },
  {
    "state": "Madhya Pradesh",
    "petrol": "106.28",
    "diesel": "91.68",
    "updated": "2026-03-01"
  },
  {
    "state": "Maharashtra",
    "petrol": "103.54",
    "diesel": "90.03",
    "updated": "2026-03-01"
  },
  {
    "state": "Manipur",
    "petrol": "99.33",
    "diesel": "85.38",
    "updated": "2026-03-01"
  },
  {
    "state": "Meghalaya",
    "petrol": "96.20",
    "diesel": "87.64",
    "updated": "2026-03-01"
  },
  {
    "state": "Mizoram",
    "petrol": "99.06",
    "diesel": "87.92",
    "updated": "2026-03-01"
  },
  {
    "state": "Nagaland",
    "petrol": "97.70",
    "diesel": "88.83",
    "updated": "2026-03-01"
  },
  {
    "state": "Odisha",
    "petrol": "101.19",
    "diesel": "92.77",
    "updated": "2026-03-01"
  },
  {
    "state": "Punjab",
    "petrol": "98.31",
    "diesel": "88.11",
    "updated": "2026-03-01"
  },
  {
    "state": "Rajasthan",
    "petrol": "104.38",
    "diesel": "89.90",
    "updated": "2026-03-01"
  },
  {
    "state": "Sikkim",
    "petrol": "103.35",
    "diesel": "90.45",
    "updated": "2026-03-01"
  },
  {
    "state": "Tamil Nadu",
    "petrol": "100.90",
    "diesel": "92.49",
    "updated": "2026-03-01"
  },
  {
    "state": "Telangana",
    "petrol": "107.46",
    "diesel": "95.70",
    "updated": "2026-03-01"
  },
  {
    "state": "Tripura",
    "petrol": "97.53",
    "diesel": "86.55",
    "updated": "2026-03-01"
  },
  {
    "state": "Uttar Pradesh",
    "petrol": "94.69",
    "diesel": "87.81",
    "updated": "2026-03-01"
  },
  {
    "state": "Uttarakhand",
    "petrol": "93.43",
    "diesel": "88.34",
    "updated": "2026-03-01"
  },
  {
    "state": "West Bengal",
    "petrol": "105.41",
    "diesel": "92.02",
    "updated": "2026-03-01"
  },
  {
    "state": "Andaman and Nicobar Islands",
    "petrol": "88.00",
    "diesel": "82.60",
    "updated": "2026-03-01"
  },
  {
    "state": "Chandigarh",
    "petrol": "94.30",
    "diesel": "82.45",
    "updated": "2026-03-01"
  },
  {
    "state": "Dadra and Nagar Haveli and Daman and Diu",
    "petrol": "92.37",
    "diesel": "87.87",
    "updated": "2026-03-01"
  },
  {
    "state": "Jammu and Kashmir",
    "petrol": "94.00",
    "diesel": "87.40",
    "updated": "2026-03-01"
  },
  {
    "state": "Ladakh",
    "petrol": "103.89",
    "diesel": "88.86",
    "updated": "2026-03-01"
  },
  {
    "state": "Lakshadweep",
    "petrol": "100.75",
    "diesel": "95.71",
    "updated": "2026-03-01"
  },
  {
    "state": "Puducherry",
    "petrol": "101.00",
    "diesel": "93.00",
    "updated": "2026-03-01"
  }
]